redis_stack_wheel/__init__.py
redis_stack_wheel/redis-stack-server/bin/redis-benchmark
redis_stack_wheel/redis-stack-server/bin/redis-check-aof
redis_stack_wheel/redis-stack-server/bin/redis-check-rdb
redis_stack_wheel/redis-stack-server/bin/redis-cli
redis_stack_wheel/redis-stack-server/bin/redis-sentinel
redis_stack_wheel/redis-stack-server/bin/redis-server
redis_stack_wheel/redis-stack-server/bin/redis-stack-server
redis_stack_wheel/redis-stack-server/etc/README
redis_stack_wheel/redis-stack-server/etc/redis-stack-service.conf
redis_stack_wheel/redis-stack-server/etc/redis-stack.conf
redis_stack_wheel/redis-stack-server/lib/libredisgears_v8_plugin.so
redis_stack_wheel/redis-stack-server/lib/redisbloom.so
redis_stack_wheel/redis-stack-server/lib/rediscompat.so
redis_stack_wheel/redis-stack-server/lib/redisearch.so
redis_stack_wheel/redis-stack-server/lib/redisgears.so
redis_stack_wheel/redis-stack-server/lib/redistimeseries.so
redis_stack_wheel/redis-stack-server/lib/rejson.so
redis_stack_wheel/redis-stack-server/share/APACHE_LICENSE
redis_stack_wheel/redis-stack-server/share/RSALv2.txt
redis_stack_wheel/redis-stack-server/share/SSPLv1.txt
redis_stack_wheel-0.1.8.dist-info/LICENSE
redis_stack_wheel-0.1.8.dist-info/METADATA
redis_stack_wheel-0.1.8.dist-info/WHEEL
redis_stack_wheel-0.1.8.dist-info/top_level.txt
redis_stack_wheel-0.1.8.dist-info/RECORD
