Metadata-Version: 2.2
Name: redis-stack-wheel
Version: 0.1.8
Summary: Wheels that bundle precompiled redis-stack-server binaries for the appropriate platform. Currently on Redis Stack v7.4.0-v1
Author-email: Benjamin Levin <bplevin36@gmail.com>
License: MIT License
Keywords: redis,server
Requires-Python: >=3.9
License-File: LICENSE
